miutil/__init__.py
miutil/_dist_ver.py
miutil/cuinfo.py
miutil/fdio.py
miutil/plot.py
miutil/web.py
miutil/imio/__init__.py
miutil/imio/nii.py
miutil/mlab/__init__.py
miutil/mlab/beautify.py
miutil-0.13.dist-info/LICENCE.md
miutil-0.13.dist-info/METADATA
miutil-0.13.dist-info/WHEEL
miutil-0.13.dist-info/entry_points.txt
miutil-0.13.dist-info/top_level.txt
miutil-0.13.dist-info/RECORD
