Metadata-Version: 2.2
Name: miutil
Version: 0.13
Summary: Medical imaging utilities for the AMYPAD and NiftyPET projects
Maintainer-email: Casper da Costa-Luis <casper.dcl@physics.org>
License: Apache-2.0
Project-URL: documentation, https://github.com/AMYPAD/miutil/#miutil
Project-URL: repository, https://github.com/AMYPAD/miutil
Project-URL: changelog, https://github.com/AMYPAD/miutil/releases
Keywords: fMRI,PET,SPECT,EEG,MEG
Classifier: Development Status :: 4 - Beta
Classifier: Intended Audience :: Developers
Classifier: Environment :: GPU
Classifier: Environment :: GPU :: NVIDIA CUDA
Classifier: Intended Audience :: Education
Classifier: Intended Audience :: Healthcare Industry
Classifier: Intended Audience :: Science/Research
Classifier: License :: OSI Approved :: Apache Software License
Classifier: Operating System :: Microsoft :: Windows
Classifier: Operating System :: POSIX :: Linux
Classifier: Programming Language :: Other Scripting Engines
Classifier: Programming Language :: Python :: 3
Classifier: Programming Language :: Python :: 3.7
Classifier: Programming Language :: Python :: 3.8
Classifier: Programming Language :: Python :: 3.9
Classifier: Programming Language :: Python :: 3.10
Classifier: Programming Language :: Python :: 3.11
Classifier: Programming Language :: Python :: 3 :: Only
Classifier: Topic :: Scientific/Engineering :: Medical Science Apps.
Classifier: Topic :: Software Development :: Libraries
Classifier: Topic :: Software Development :: Libraries :: Python Modules
Classifier: Topic :: Software Development :: User Interfaces
Classifier: Topic :: System :: Installation/Setup
Classifier: Topic :: Utilities
Requires-Python: >=3.7
License-File: LICENCE.md
Requires-Dist: tqdm>=4.40.0
Provides-Extra: dev
Requires-Dist: pytest>=6; extra == "dev"
Requires-Dist: pytest-cov; extra == "dev"
Requires-Dist: pytest-timeout; extra == "dev"
Requires-Dist: pytest-xdist; extra == "dev"
Provides-Extra: nii
Requires-Dist: nibabel>=4.0; extra == "nii"
Requires-Dist: numpy; extra == "nii"
Provides-Extra: plot
Requires-Dist: matplotlib; extra == "plot"
Requires-Dist: numpy; extra == "plot"
Requires-Dist: scipy; extra == "plot"
Provides-Extra: cuda
Requires-Dist: argopt; extra == "cuda"
Requires-Dist: pynvml; extra == "cuda"
Provides-Extra: web
Requires-Dist: requests; extra == "web"
Provides-Extra: mbeautify
Requires-Dist: argopt; extra == "mbeautify"
Requires-Dist: tqdm>=4.42.0; extra == "mbeautify"
Requires-Dist: requests; extra == "mbeautify"
